MANIFEST.in
setup.py
a1lite/__init__.py
a1lite/a1lite_settings.py
a1lite/admin.py
a1lite/models.py
a1lite/signals.py
a1lite/urls.py
a1lite/views.py
a1lite/fixtures/initial_data.json
a1lite/locale/ru/LC_MESSAGES/django.mo
a1lite/locale/ru/LC_MESSAGES/django.po
a1lite/migrations/0001_initial.py
a1lite/migrations/0002_auto__chg_field_payment_tid.py
a1lite/migrations/0003_auto__chg_field_payment_system_income__chg_field_payment_partner_incom.py
a1lite/migrations/__init__.py
a1lite/templates/a1lite/a1lite_form.html
a1lite/templates/a1lite/a1lite_form_button.html
a1lite/templates/a1lite/error.html
a1lite/templates/a1lite/success.html
a1lite/templatetags/__init__.py
a1lite/templatetags/a1lite.py
django_a1lite.egg-info/PKG-INFO
django_a1lite.egg-info/SOURCES.txt
django_a1lite.egg-info/dependency_links.txt
django_a1lite.egg-info/not-zip-safe
django_a1lite.egg-info/top_level.txt