Metadata-Version: 1.1
Name: django-a1lite
Version: 0.5
Summary: django application for using http://a1pay.ru/ payment gateway
Home-page: https://github.com/dgk/django_a1lite
Author: Dmitry Kuksinsky
Author-email: dgk@dgk.su
License: BSD
Platform: UNKNOWN
Classifier: Development Status :: 3 - Alpha
Classifier: Environment :: Web Environment
Classifier: Intended Audience :: Developers
Classifier: License :: OSI Approved :: BSD License
Classifier: Operating System :: OS Independent
Classifier: Programming Language :: Python
Classifier: Framework :: Django
